mxmc/__init__.py
mxmc/estimator.py
mxmc/optimizer.py
mxmc/output_processor.py
mxmc/estimators/__init__.py
mxmc/estimators/acv_estimator.py
mxmc/estimators/estimator_base.py
mxmc/estimators/mlmc_estimator.py
mxmc/optimizers/__init__.py
mxmc/optimizers/mfmc.py
mxmc/optimizers/mlmc.py
mxmc/optimizers/model_selection.py
mxmc/optimizers/optimizer_base.py
mxmc/optimizers/approximate_control_variates/__init__.py
mxmc/optimizers/approximate_control_variates/acv_constraints.py
mxmc/optimizers/approximate_control_variates/acv_optimizer.py
mxmc/optimizers/approximate_control_variates/recursion_enumerator.py
mxmc/optimizers/approximate_control_variates/generalized_independent_samples/__init__.py
mxmc/optimizers/approximate_control_variates/generalized_independent_samples/gis_optimizer.py
mxmc/optimizers/approximate_control_variates/generalized_independent_samples/impl_optimizers.py
mxmc/optimizers/approximate_control_variates/generalized_multifidelity/__init__.py
mxmc/optimizers/approximate_control_variates/generalized_multifidelity/gmf_optimizer.py
mxmc/optimizers/approximate_control_variates/generalized_multifidelity/gmf_ordered.py
mxmc/optimizers/approximate_control_variates/generalized_multifidelity/gmf_unordered.py
mxmc/optimizers/approximate_control_variates/generalized_multifidelity/impl_optimizers.py
mxmc/optimizers/approximate_control_variates/generalized_recursive_difference/__init__.py
mxmc/optimizers/approximate_control_variates/generalized_recursive_difference/grd_optimizer.py
mxmc/optimizers/approximate_control_variates/generalized_recursive_difference/impl_optimizers.py
mxmc/sample_allocations/__init__.py
mxmc/sample_allocations/acv_sample_allocation.py
mxmc/sample_allocations/mlmc_sample_allocation.py
mxmc/sample_allocations/sample_allocation_base.py
mxmc/util/__init__.py
mxmc/util/generic_numerical_optimization.py
mxmc/util/read_sample_allocation.py
mxmc/util/sample_modification.py
mxmc/util/testing.py
mxmcpy-1.0.dist-info/LICENSE
mxmcpy-1.0.dist-info/METADATA
mxmcpy-1.0.dist-info/WHEEL
mxmcpy-1.0.dist-info/top_level.txt
mxmcpy-1.0.dist-info/RECORD
