Metadata-Version: 2.1
Name: mxmcpy
Version: 1.0
Summary: Multi Model Monte Carlo with Python
Home-page: https://github.com/nasa/MXMCPy
Author: Geoffrey F. Bomarito, James E. Warner, Patrick E. Leser, William P. Leser, Luke Morrill
Author-email: 
License: UNKNOWN
Platform: UNKNOWN
Classifier: Programming Language :: Python :: 3
Classifier: License :: OSI Approved :: Apache Software License
Classifier: Operating System :: OS Independent
Classifier: Intended Audience :: Science/Research
Requires-Python: >=3.7
Requires-Dist: numpy
Requires-Dist: pandas
Requires-Dist: scipy
Requires-Dist: torch
Requires-Dist: h5py
